{"player": {"spawn": "100,250", "size": "50,50", "hp": 100}, "enemy": [{"spawn": "150,50", "size": "50,50", "facing": "right", "hp": 50, "firingDamage": 25, "firingRate": 1000}, {"spawn": "600,300", "size": "50,50", "facing": "left", "hp": 50, "firingDamage": 25, "firingRate": 1000}, {"spawn": "600,200", "size": "50,50", "facing": "left", "hp": 50, "firingDamage": 25, "firingRate": 1000}, {"spawn": "600,100", "size": "50,50", "facing": "left", "hp": 50, "firingDamage": 25, "firingRate": 1000}, {"spawn": "800,500", "size": "50,50", "facing": "left", "hp": 50, "firingDamage": 25, "firingRate": 1000}], "collidable": [{"spawn": "100,100", "size": "50,50"}, {"spawn": "150,100", "size": "50,50"}, {"spawn": "350,200", "size": "50,50"}, {"spawn": "400,250", "size": "50,50"}, {"spawn": "450,300", "size": "50,50"}, {"spawn": "500,350", "size": "50,50"}, {"spawn": "250,150", "size": "50,50"}, {"spawn": "300,150", "size": "50,50"}, {"spawn": "250,100", "size": "50,50"}, {"spawn": "200,100", "size": "50,50"}, {"spawn": "450,350", "size": "50,50"}, {"spawn": "400,300", "size": "50,50"}, {"spawn": "350,250", "size": "50,50"}, {"spawn": "300,200", "size": "50,50"}, {"spawn": "200,350", "size": "50,50"}, {"spawn": "400,550", "size": "50,50"}, {"spawn": "450,550", "size": "50,50"}, {"spawn": "500,550", "size": "50,50"}, {"spawn": "550,550", "size": "50,50"}, {"spawn": "600,550", "size": "50,50"}, {"spawn": "650,550", "size": "50,50"}, {"spawn": "700,550", "size": "50,50"}, {"spawn": "750,550", "size": "50,50"}, {"spawn": "800,550", "size": "50,50"}, {"spawn": "850,550", "size": "50,50"}, {"spawn": "300,500", "size": "100,100"}, {"spawn": "200,500", "size": "100,100"}, {"spawn": "200,400", "size": "100,100"}, {"spawn": "650,50", "size": "50,50"}, {"spawn": "100,300", "size": "100,100"}, {"spawn": "550,350", "size": "50,50"}, {"spawn": "600,350", "size": "50,50"}, {"spawn": "650,350", "size": "50,50"}, {"spawn": "650,300", "size": "50,50"}, {"spawn": "650,250", "size": "50,50"}, {"spawn": "650,200", "size": "50,50"}, {"spawn": "650,150", "size": "50,50"}, {"spawn": "650,100", "size": "50,50"}, {"spawn": "600,50", "size": "50,50"}, {"spawn": "850,500", "size": "50,50"}, {"spawn": "850,450", "size": "50,50"}, {"spawn": "850,400", "size": "50,50"}, {"spawn": "850,350", "size": "50,50"}, {"spawn": "850,300", "size": "50,50"}, {"spawn": "850,250", "size": "50,50"}, {"spawn": "850,200", "size": "50,50"}, {"spawn": "850,150", "size": "50,50"}, {"spawn": "850,100", "size": "50,50"}, {"spawn": "850,50", "size": "50,50"}, {"spawn": "825,450", "size": "25,25"}, {"spawn": "800,450", "size": "25,25"}, {"spawn": "850,0", "size": "50,50"}, {"spawn": "700,350", "size": "25,25"}, {"spawn": "725,350", "size": "25,25"}, {"spawn": "800,250", "size": "25,25"}, {"spawn": "825,250", "size": "25,25"}, {"spawn": "700,150", "size": "25,25"}, {"spawn": "725,150", "size": "25,25"}, {"spawn": "800,50", "size": "25,25"}, {"spawn": "825,50", "size": "25,25"}], "objective": {"spawn": "100,50", "size": "50,50"}, "fatal": [], "booster": []}